syndirella/__init__.py
syndirella/__main__.py
syndirella/cli.py
syndirella/cli_defaults.py
syndirella/justretroquery.py
syndirella/pipeline.py
syndirella/aizynth/AiZynthManager.py
syndirella/aizynth/__init__.py
syndirella/constants/ADDITIONAL_RXN_OPTIONS.json
syndirella/constants/REACTANT_FILTER_CONSTANTS.json
syndirella/constants/RXN_SMIRKS_CONSTANTS.json
syndirella/constants/__init__.py
syndirella/constants/uspto_template_lookup.json.gz
syndirella/database/Arthor.py
syndirella/database/DatabaseSearch.py
syndirella/database/Hippo.py
syndirella/database/Postera.py
syndirella/database/__init__.py
syndirella/route/Cobbler.py
syndirella/route/CobblerBench.py
syndirella/route/CobblersWorkshop.py
syndirella/route/Library.py
syndirella/route/Reaction.py
syndirella/route/SMARTSHandler.py
syndirella/route/SmirksLibraryManager.py
syndirella/route/__init__.py
syndirella/slipper/Slipper.py
syndirella/slipper/SlipperFitter.py
syndirella/slipper/__init__.py
syndirella/slipper/_placement_data.py
syndirella/slipper/flatness.py
syndirella/slipper/intra_geometry.py
syndirella/slipper/stats.py
syndirella/slipper/slipper_synthesizer/Labeler.py
syndirella/slipper/slipper_synthesizer/SlipperSynthesizer.py
syndirella/slipper/slipper_synthesizer/__init__.py
syndirella/tests/__init__.py
syndirella/tests/read_structured_output.ipynb
syndirella/tests/test_add_reaction.py
syndirella/tests/test_additional_routes.py
syndirella/tests/test_arthor_integration.py
syndirella/tests/test_error_handling.py
syndirella/tests/test_full_cli.py
syndirella/tests/test_inputs.py
syndirella/tests/test_justretroquery.py
syndirella/tests/test_pipeline_mocked.py
syndirella/tests/test_pipeline_real.py
syndirella/tests/test_placements.py
syndirella/tests/test_route_handling.py
syndirella/tests/test_template_loader.py
syndirella/tests/inputs/test_error_handling/CHIKV_Mac_combined.sdf
syndirella/tests/inputs/test_error_handling/cx0270a_apo-desolv.pdb
syndirella/tests/inputs/test_error_handling/no_synthesis_route.csv
syndirella-5.0.5a0.dist-info/licenses/LICENSE
syndirella-5.0.5a0.dist-info/METADATA
syndirella-5.0.5a0.dist-info/WHEEL
syndirella-5.0.5a0.dist-info/entry_points.txt
syndirella-5.0.5a0.dist-info/top_level.txt
syndirella-5.0.5a0.dist-info/RECORD
