Metadata-Version: 2.4
Name: syndirella
Version: 5.0.5a0
Summary: Synthetically Driven Elaborations
Author-email: Kate Fieseler <kate.k.fieseler@gmail.com>
Project-URL: Documentation, https://syndirella.readthedocs.io/en/latest/
Project-URL: Source, https://github.com/kate-fie/syndirella
Project-URL: Bug Tracker, https://github.com/kate-fie/syndirella/issues
Classifier: Programming Language :: Python :: 3
Classifier: License :: OSI Approved :: MIT License
Classifier: Operating System :: OS Independent
Requires-Python: <3.11,>=3.10
License-File: LICENSE
Requires-Dist: rdkit
Requires-Dist: jupyter
Requires-Dist: numpy<2
Requires-Dist: glob2
Requires-Dist: requests
Requires-Dist: pillow
Requires-Dist: fragmenstein>=1.0.7
Requires-Dist: shortuuid
Requires-Dist: pandas
Requires-Dist: biopython
Requires-Dist: aizynthfinder
Requires-Dist: matplotlib
Requires-Dist: seaborn
Requires-Dist: scikit-learn
Requires-Dist: pyyaml
Requires-Dist: openpyxl
Requires-Dist: xlrd
Dynamic: license-file
